{
  "profile": {
    "code": "7613",
    "name": "シークス",
    "sector33Name": "卸売業",
    "sector33Code": "6050",
    "sector17Code": "13",
    "marketSegment": "プライム",
    "scaleCategory": "TOPIX Small 1",
    "updatedAt": "2026-04-26T09:37:44.799Z",
    "snapshots": [
      {
        "id": "static-7613",
        "snapshotAt": "2026-04-26T09:37:44.799Z",
        "marketCap": 58356414414,
        "netCash": -103339000000,
        "netCashRatio": -1.7708250419033362,
        "cashNeutralPer": 37.60358474744186,
        "per": 13.571259166046511,
        "pbr": 0.5885254133747492
      }
    ]
  },
  "history": [
    {
      "id": "static-7613-2025-3Q",
      "code": "7613",
      "fiscalYear": 2025,
      "typeOfCurrentPeriod": "3Q",
      "disclosedDate": "2025-11-07T00:00:00.000Z",
      "periodEndDate": "2025-09-30T00:00:00.000Z",
      "netSales": 214435000000,
      "operatingProfit": 6808000000,
      "ordinaryProfit": null,
      "profit": 4300000000,
      "totalAssets": 202496000000,
      "equity": 99157000000,
      "cashAndEquivalents": null,
      "sharesOutstanding": 47137653
    }
  ],
  "strategies": {
    "kiyohara": {
      "score": 0,
      "components": {
        "ncrScore": 1,
        "cnperScore": -8,
        "sizeBonus": -10
      },
      "reason": "NCR=-1.77, CNPER=37.6, 大型株ペナルティ → 対象外"
    }
  }
}