{
  "profile": {
    "code": "3799",
    "name": "キーウェアソリューションズ",
    "sector33Name": "情報･通信業",
    "sector33Code": "5250",
    "sector17Code": "10",
    "marketSegment": "スタンダード",
    "scaleCategory": "-",
    "updatedAt": "2026-04-26T09:37:38.949Z",
    "snapshots": [
      {
        "id": "static-3799",
        "snapshotAt": "2026-04-26T09:37:38.949Z",
        "marketCap": 10694137233,
        "netCash": -3024000000,
        "netCashRatio": -0.28277175934011134,
        "cashNeutralPer": 61.241684075892856,
        "per": 47.741684075892856,
        "pbr": 1.4173806803180915
      }
    ]
  },
  "history": [
    {
      "id": "static-3799-2025-2Q",
      "code": "3799",
      "fiscalYear": 2025,
      "typeOfCurrentPeriod": "2Q",
      "disclosedDate": "2025-10-30T00:00:00.000Z",
      "periodEndDate": "2025-09-30T00:00:00.000Z",
      "netSales": 10721000000,
      "operatingProfit": 300000000,
      "ordinaryProfit": null,
      "profit": 224000000,
      "totalAssets": 10569000000,
      "equity": 7545000000,
      "cashAndEquivalents": 2456981000,
      "sharesOutstanding": 8361327
    }
  ],
  "strategies": {
    "kiyohara": {
      "score": 0,
      "components": {
        "ncrScore": 9,
        "cnperScore": -15,
        "sizeBonus": 0
      },
      "reason": "NCR=-0.28, CNPER=61.2, 107億円 → 対象外"
    }
  }
}