{
  "profile": {
    "code": "7649",
    "name": "スギホールディングス",
    "sector33Name": "小売業",
    "sector33Code": "6100",
    "sector17Code": "14",
    "marketSegment": "プライム",
    "scaleCategory": "TOPIX Mid400",
    "updatedAt": "2026-04-26T09:37:44.854Z",
    "snapshots": [
      {
        "id": "static-7649",
        "snapshotAt": "2026-04-26T09:37:44.854Z",
        "marketCap": 674123791750,
        "netCash": -335319000000,
        "netCashRatio": -0.4974145759334862,
        "cashNeutralPer": 28.30186984467435,
        "per": 18.900490418313847,
        "pbr": 2.4028136691070587
      }
    ]
  },
  "history": [
    {
      "id": "static-7649-2025-3Q",
      "code": "7649",
      "fiscalYear": 2025,
      "typeOfCurrentPeriod": "3Q",
      "disclosedDate": "2026-01-08T00:00:00.000Z",
      "periodEndDate": "2025-11-30T00:00:00.000Z",
      "netSales": 750127000000,
      "operatingProfit": 34137000000,
      "ordinaryProfit": null,
      "profit": 35667000000,
      "totalAssets": 615875000000,
      "equity": 280556000000,
      "cashAndEquivalents": null,
      "sharesOutstanding": 180972830
    },
    {
      "id": "static-7649-2025-2Q",
      "code": "7649",
      "fiscalYear": 2025,
      "typeOfCurrentPeriod": "2Q",
      "disclosedDate": "2025-10-09T00:00:00.000Z",
      "periodEndDate": "2025-08-31T00:00:00.000Z",
      "netSales": 500172000000,
      "operatingProfit": 23696000000,
      "ordinaryProfit": null,
      "profit": 28616000000,
      "totalAssets": 554801000000,
      "equity": 276292000000,
      "cashAndEquivalents": 109298000000,
      "sharesOutstanding": 180972937
    }
  ],
  "strategies": {
    "kiyohara": {
      "score": 0,
      "components": {
        "ncrScore": 8,
        "cnperScore": -8,
        "sizeBonus": -10
      },
      "reason": "NCR=-0.50, CNPER=28.3, 大型株ペナルティ → 対象外"
    }
  }
}