{
  "profile": {
    "code": "5287",
    "name": "イトーヨーギョー",
    "sector33Name": "ガラス･土石製品",
    "sector33Code": "3400",
    "sector17Code": "3",
    "marketSegment": "スタンダード",
    "scaleCategory": "-",
    "updatedAt": "2026-04-26T09:37:43.195Z",
    "snapshots": [
      {
        "id": "static-5287",
        "snapshotAt": "2026-04-26T09:37:43.195Z",
        "marketCap": 3624555739,
        "netCash": -1701000000,
        "netCashRatio": -0.46929889412303505,
        "cashNeutralPer": 96.82828616363636,
        "per": 65.90101343636364,
        "pbr": 0.9769692018867925
      }
    ]
  },
  "history": [
    {
      "id": "static-5287-2025-2Q",
      "code": "5287",
      "fiscalYear": 2025,
      "typeOfCurrentPeriod": "2Q",
      "disclosedDate": "2025-11-07T00:00:00.000Z",
      "periodEndDate": "2025-09-30T00:00:00.000Z",
      "netSales": 1575000000,
      "operatingProfit": 104000000,
      "ordinaryProfit": null,
      "profit": 55000000,
      "totalAssets": 5411000000,
      "equity": 3710000000,
      "cashAndEquivalents": null,
      "sharesOutstanding": 2949191
    }
  ],
  "strategies": {
    "kiyohara": {
      "score": 0,
      "components": {
        "ncrScore": 8,
        "cnperScore": -15,
        "sizeBonus": 5
      },
      "reason": "NCR=-0.47, CNPER=96.8, 36億円 → 対象外"
    }
  }
}