{
  "profile": {
    "code": "4172",
    "name": "Ｈｉクラテス",
    "sector33Name": "情報･通信業",
    "sector33Code": "5250",
    "sector17Code": "10",
    "marketSegment": "スタンダード",
    "scaleCategory": "-",
    "updatedAt": "2026-05-13T13:41:23.058Z",
    "snapshots": [
      {
        "id": "static-4172",
        "snapshotAt": "2026-05-13T13:41:23.058Z",
        "marketCap": 5362398845,
        "netCash": -525000000,
        "netCashRatio": -0.09790394470368792,
        "cashNeutralPer": 13.141515279017858,
        "per": 11.969640279017858,
        "pbr": 1.277978752383222
      }
    ]
  },
  "history": [
    {
      "id": "static-4172-2025-1Q",
      "code": "4172",
      "fiscalYear": 2025,
      "typeOfCurrentPeriod": "1Q",
      "disclosedDate": "2026-02-13T00:00:00.000Z",
      "periodEndDate": "2025-12-31T00:00:00.000Z",
      "netSales": 632000000,
      "operatingProfit": 187000000,
      "ordinaryProfit": null,
      "profit": 136000000,
      "totalAssets": 4578000000,
      "equity": 4228000000,
      "cashAndEquivalents": null,
      "sharesOutstanding": 2227835
    },
    {
      "id": "static-4172-2025-FY",
      "code": "4172",
      "fiscalYear": 2025,
      "typeOfCurrentPeriod": "FY",
      "disclosedDate": "2025-11-11T00:00:00.000Z",
      "periodEndDate": "2025-09-30T00:00:00.000Z",
      "netSales": 2406000000,
      "operatingProfit": 549000000,
      "ordinaryProfit": null,
      "profit": 448000000,
      "totalAssets": 4721000000,
      "equity": 4196000000,
      "cashAndEquivalents": 1103000000,
      "sharesOutstanding": 2227835
    }
  ],
  "strategies": {
    "kiyohara": {
      "score": 21,
      "components": {
        "ncrScore": 10,
        "cnperScore": 8,
        "sizeBonus": 3
      },
      "reason": "NCR=-0.10, CNPER=13.1, 54億円 → 割高気味"
    },
    "graham": {
      "score": 65,
      "components": {
        "grahamProductScore": 41,
        "pbrScore": 12,
        "perScore": 12,
        "ncrBonus": 0
      },
      "reason": "PBR×PER=15.3, PBR=1.28, PER=12.0 → 買い候補"
    },
    "buffett": {
      "score": 25,
      "components": {
        "roeScore": 25,
        "qualityBonus": 0,
        "valuationPenalty": 0
      },
      "reason": "ROE=10.7%, PBR=1.28 → 様子見"
    },
    "lynch": {
      "score": 48,
      "components": {
        "perScore": 38,
        "sizeBonus": 10,
        "pbrPenalty": 0
      },
      "reason": "PER=12.0, 時価総額54億 → 注目"
    },
    "dividend": {
      "score": 50,
      "components": {
        "earningsYieldScore": 50,
        "stabilityBonus": 0,
        "pbrPenalty": 0
      },
      "reason": "益回り8.35%, NCR=-0.10, PBR=1.28 → 良好"
    },
    "composite": {
      "score": 42,
      "components": {
        "kiyohara": 21,
        "graham": 65,
        "buffett": 25,
        "lynch": 48,
        "dividend": 50
      },
      "reason": "総合(均等加重): 清原流:21, グレアム流:65, バフェット流:25, リンチ流:48, 配当・インカム流:50"
    }
  }
}