{
  "profile": {
    "code": "2266",
    "name": "六甲バター",
    "sector33Name": "食料品",
    "sector33Code": "3050",
    "sector17Code": "1",
    "marketSegment": "プライム",
    "scaleCategory": "TOPIX Small 2",
    "updatedAt": "2026-04-26T09:37:35.900Z",
    "snapshots": [
      {
        "id": "static-2266",
        "snapshotAt": "2026-04-26T09:37:35.900Z",
        "marketCap": 22736497620,
        "netCash": -19731000000,
        "netCashRatio": -0.8678117593029704,
        "cashNeutralPer": 83.106648962818,
        "per": 44.49412450097847,
        "pbr": 0.7263592620279854
      }
    ]
  },
  "history": [
    {
      "id": "static-2266-2025-3Q",
      "code": "2266",
      "fiscalYear": 2025,
      "typeOfCurrentPeriod": "3Q",
      "disclosedDate": "2025-11-07T00:00:00.000Z",
      "periodEndDate": "2025-09-30T00:00:00.000Z",
      "netSales": 31000000000,
      "operatingProfit": 744000000,
      "ordinaryProfit": null,
      "profit": 511000000,
      "totalAssets": 51033000000,
      "equity": 31302000000,
      "cashAndEquivalents": null,
      "sharesOutstanding": 19482860
    }
  ],
  "strategies": {
    "kiyohara": {
      "score": 0,
      "components": {
        "ncrScore": 6,
        "cnperScore": -15,
        "sizeBonus": 0
      },
      "reason": "NCR=-0.87, CNPER=83.1, 227億円 → 対象外"
    }
  }
}