{
  "profile": {
    "code": "6977",
    "name": "日本抵抗器製作所",
    "sector33Name": "電気機器",
    "sector33Code": "3650",
    "sector17Code": "9",
    "marketSegment": "スタンダード",
    "scaleCategory": "-",
    "updatedAt": "2026-05-13T13:41:23.301Z",
    "snapshots": [
      {
        "id": "static-6977",
        "snapshotAt": "2026-05-13T13:41:23.301Z",
        "marketCap": 1158022008,
        "netCash": -5554000000,
        "netCashRatio": -4.7961091944981415,
        "cashNeutralPer": null,
        "per": null,
        "pbr": 0.7001342249093108
      }
    ]
  },
  "history": [
    {
      "id": "static-6977-2025-FY",
      "code": "6977",
      "fiscalYear": 2025,
      "typeOfCurrentPeriod": "FY",
      "disclosedDate": "2026-02-16T00:00:00.000Z",
      "periodEndDate": "2025-12-31T00:00:00.000Z",
      "netSales": 5905000000,
      "operatingProfit": -109000000,
      "ordinaryProfit": null,
      "profit": -376000000,
      "totalAssets": 7208000000,
      "equity": 1654000000,
      "cashAndEquivalents": 1459000000,
      "sharesOutstanding": 1237203
    },
    {
      "id": "static-6977-2025-3Q",
      "code": "6977",
      "fiscalYear": 2025,
      "typeOfCurrentPeriod": "3Q",
      "disclosedDate": "2025-11-14T00:00:00.000Z",
      "periodEndDate": "2025-09-30T00:00:00.000Z",
      "netSales": 4177000000,
      "operatingProfit": -164000000,
      "ordinaryProfit": null,
      "profit": -244000000,
      "totalAssets": 7457000000,
      "equity": 1707000000,
      "cashAndEquivalents": null,
      "sharesOutstanding": 1237203
    }
  ],
  "strategies": {
    "kiyohara": {
      "score": 5,
      "components": {
        "ncrScore": 0,
        "cnperScore": 0,
        "sizeBonus": 5
      },
      "reason": "NCR=-4.80, CNPER=null, 12億円、赤字キャップ → 対象外"
    },
    "graham": {
      "score": 0,
      "components": {
        "grahamProductScore": null,
        "pbrScore": null,
        "perScore": null,
        "ncrBonus": null
      },
      "reason": "データ不足（PER/PBR/純資産が必要）"
    },
    "buffett": {
      "score": 0,
      "components": {
        "roeScore": 0,
        "qualityBonus": 0,
        "valuationPenalty": 0
      },
      "reason": "ROE=n/a, PBR=0.70、赤字キャップ → 対象外"
    },
    "lynch": {
      "score": 0,
      "components": {
        "perScore": null,
        "sizeBonus": null,
        "pbrPenalty": null
      },
      "reason": "データ不足（PERが必要）"
    },
    "dividend": {
      "score": 0,
      "components": {
        "earningsYieldScore": null,
        "stabilityBonus": null,
        "pbrPenalty": null
      },
      "reason": "赤字（インカム不適）"
    },
    "composite": {
      "score": 1,
      "components": {
        "kiyohara": 5,
        "graham": 0,
        "buffett": 0,
        "lynch": 0,
        "dividend": 0
      },
      "reason": "総合(均等加重): 清原流:5, グレアム流:0, バフェット流:0, リンチ流:0, 配当・インカム流:0"
    }
  }
}