{
  "profile": {
    "code": "4373",
    "name": "シンプレクス・ホールディングス",
    "sector33Name": "情報･通信業",
    "sector33Code": "5250",
    "sector17Code": "10",
    "marketSegment": "プライム",
    "scaleCategory": "TOPIX Small 1",
    "updatedAt": "2026-04-26T09:37:41.382Z",
    "snapshots": [
      {
        "id": "static-4373",
        "snapshotAt": "2026-04-26T09:37:41.382Z",
        "marketCap": 53272891925,
        "netCash": -27893000000,
        "netCashRatio": -0.5235871189284981,
        "cashNeutralPer": 16.990975910613354,
        "per": 11.151955604982206,
        "pbr": 1.057379459429955
      }
    ]
  },
  "history": [
    {
      "id": "static-4373-2025-2Q",
      "code": "4373",
      "fiscalYear": 2025,
      "typeOfCurrentPeriod": "2Q",
      "disclosedDate": "2025-10-30T00:00:00.000Z",
      "periodEndDate": "2025-09-30T00:00:00.000Z",
      "netSales": 27801000000,
      "operatingProfit": 7055000000,
      "ordinaryProfit": null,
      "profit": 4777000000,
      "totalAssets": 78275000000,
      "equity": 50382000000,
      "cashAndEquivalents": 15827000000,
      "sharesOutstanding": 56976355
    }
  ],
  "strategies": {
    "kiyohara": {
      "score": 0,
      "components": {
        "ncrScore": 7,
        "cnperScore": 0,
        "sizeBonus": -10
      },
      "reason": "NCR=-0.52, CNPER=17.0, 大型株ペナルティ → 対象外"
    }
  }
}