{
  "profile": {
    "code": "6965",
    "name": "浜松ホトニクス",
    "sector33Name": "電気機器",
    "sector33Code": "3650",
    "sector17Code": "9",
    "marketSegment": "プライム",
    "scaleCategory": "TOPIX Mid400",
    "updatedAt": "2026-04-26T09:37:44.461Z",
    "snapshots": [
      {
        "id": "static-6965",
        "snapshotAt": "2026-04-26T09:37:44.461Z",
        "marketCap": 508790296352,
        "netCash": -131553000000,
        "netCashRatio": -0.25856035569708813,
        "cashNeutralPer": 45.08507331915792,
        "per": 35.822734376680984,
        "pbr": 1.5729863392187475
      }
    ]
  },
  "history": [
    {
      "id": "static-6965-2025-FY",
      "code": "6965",
      "fiscalYear": 2025,
      "typeOfCurrentPeriod": "FY",
      "disclosedDate": "2025-11-07T00:00:00.000Z",
      "periodEndDate": "2025-09-30T00:00:00.000Z",
      "netSales": 212051000000,
      "operatingProfit": 16163000000,
      "ordinaryProfit": null,
      "profit": 14203000000,
      "totalAssets": 455008000000,
      "equity": 323455000000,
      "cashAndEquivalents": 86037000000,
      "sharesOutstanding": 298761184
    }
  ],
  "strategies": {
    "kiyohara": {
      "score": 0,
      "components": {
        "ncrScore": 9,
        "cnperScore": -15,
        "sizeBonus": -10
      },
      "reason": "NCR=-0.26, CNPER=45.1, 大型株ペナルティ → 対象外"
    }
  }
}