{
  "profile": {
    "code": "8084",
    "name": "ＲＹＯＤＥＮ",
    "sector33Name": "卸売業",
    "sector33Code": "6050",
    "sector17Code": "13",
    "marketSegment": "プライム",
    "scaleCategory": "TOPIX Small 2",
    "updatedAt": "2026-05-13T13:41:23.418Z",
    "snapshots": [
      {
        "id": "static-8084",
        "snapshotAt": "2026-05-13T13:41:23.418Z",
        "marketCap": 77929129785,
        "netCash": -58022000000,
        "netCashRatio": -0.7445482858602153,
        "cashNeutralPer": 39.88006153857436,
        "per": 22.859820998826635,
        "pbr": 0.8661294350034454
      }
    ]
  },
  "history": [
    {
      "id": "static-8084-2025-3Q",
      "code": "8084",
      "fiscalYear": 2025,
      "typeOfCurrentPeriod": "3Q",
      "disclosedDate": "2026-01-30T00:00:00.000Z",
      "periodEndDate": "2025-12-31T00:00:00.000Z",
      "netSales": 153844000000,
      "operatingProfit": 3151000000,
      "ordinaryProfit": null,
      "profit": 3409000000,
      "totalAssets": 147996000000,
      "equity": 89974000000,
      "cashAndEquivalents": 38173000000,
      "sharesOutstanding": 21557159
    },
    {
      "id": "static-8084-2025-2Q",
      "code": "8084",
      "fiscalYear": 2025,
      "typeOfCurrentPeriod": "2Q",
      "disclosedDate": "2025-10-31T00:00:00.000Z",
      "periodEndDate": "2025-09-30T00:00:00.000Z",
      "netSales": 102062000000,
      "operatingProfit": 2433000000,
      "ordinaryProfit": null,
      "profit": 2172000000,
      "totalAssets": 141987000000,
      "equity": 89462000000,
      "cashAndEquivalents": 38661000000,
      "sharesOutstanding": 21557266
    }
  ],
  "strategies": {
    "kiyohara": {
      "score": 0,
      "components": {
        "ncrScore": 6,
        "cnperScore": -8,
        "sizeBonus": -10
      },
      "reason": "NCR=-0.74, CNPER=39.9, 大型株ペナルティ → 対象外"
    },
    "graham": {
      "score": 51,
      "components": {
        "grahamProductScore": 31,
        "pbrScore": 20,
        "perScore": 0,
        "ncrBonus": 0
      },
      "reason": "PBR×PER=19.8, PBR=0.87, PER=22.9 → 買い候補"
    },
    "buffett": {
      "score": 0,
      "components": {
        "roeScore": 0,
        "qualityBonus": 0,
        "valuationPenalty": 0
      },
      "reason": "ROE=3.8%, PBR=0.87 → 対象外"
    },
    "lynch": {
      "score": 8,
      "components": {
        "perScore": 8,
        "sizeBonus": 0,
        "pbrPenalty": 0
      },
      "reason": "PER=22.9, 時価総額779億 → 対象外"
    },
    "dividend": {
      "score": 18,
      "components": {
        "earningsYieldScore": 18,
        "stabilityBonus": 0,
        "pbrPenalty": 0
      },
      "reason": "益回り4.37%, NCR=-0.74, PBR=0.87 → 対象外"
    },
    "composite": {
      "score": 15,
      "components": {
        "kiyohara": 0,
        "graham": 51,
        "buffett": 0,
        "lynch": 8,
        "dividend": 18
      },
      "reason": "総合(均等加重): 清原流:0, グレアム流:51, バフェット流:0, リンチ流:8, 配当・インカム流:18"
    }
  }
}