{
  "profile": {
    "code": "9845",
    "name": "パーカーコーポレーション",
    "sector33Name": "化学",
    "sector33Code": "3200",
    "sector17Code": "4",
    "marketSegment": "スタンダード",
    "scaleCategory": "-",
    "updatedAt": "2026-04-26T09:37:46.114Z",
    "snapshots": [
      {
        "id": "static-9845",
        "snapshotAt": "2026-04-26T09:37:46.114Z",
        "marketCap": 37667827785,
        "netCash": -22188000000,
        "netCashRatio": -0.5890437889501995,
        "cashNeutralPer": 24.341532242781618,
        "per": 15.318352088247256,
        "pbr": 0.7551538217958742
      }
    ]
  },
  "history": [
    {
      "id": "static-9845-2025-2Q",
      "code": "9845",
      "fiscalYear": 2025,
      "typeOfCurrentPeriod": "2Q",
      "disclosedDate": "2025-11-04T00:00:00.000Z",
      "periodEndDate": "2025-09-30T00:00:00.000Z",
      "netSales": 34766000000,
      "operatingProfit": 3274000000,
      "ordinaryProfit": null,
      "profit": 2459000000,
      "totalAssets": 72069000000,
      "equity": 49881000000,
      "cashAndEquivalents": 19558000000,
      "sharesOutstanding": 25028457
    }
  ],
  "strategies": {
    "kiyohara": {
      "score": 0,
      "components": {
        "ncrScore": 7,
        "cnperScore": -8,
        "sizeBonus": 0
      },
      "reason": "NCR=-0.59, CNPER=24.3, 377億円 → 対象外"
    }
  }
}