{
  "profile": {
    "code": "9622",
    "name": "スペース",
    "sector33Name": "サービス業",
    "sector33Code": "9050",
    "sector17Code": "10",
    "marketSegment": "プライム",
    "scaleCategory": "TOPIX Small 2",
    "updatedAt": "2026-04-26T09:37:46.079Z",
    "snapshots": [
      {
        "id": "static-9622",
        "snapshotAt": "2026-04-26T09:37:46.079Z",
        "marketCap": 38028975650,
        "netCash": -11219000000,
        "netCashRatio": -0.2950118904925066,
        "cashNeutralPer": 19.962697871909203,
        "per": 15.415069173084719,
        "pbr": 1.13529497119145
      }
    ]
  },
  "history": [
    {
      "id": "static-9622-2025-3Q",
      "code": "9622",
      "fiscalYear": 2025,
      "typeOfCurrentPeriod": "3Q",
      "disclosedDate": "2025-11-12T00:00:00.000Z",
      "periodEndDate": "2025-09-30T00:00:00.000Z",
      "netSales": 51062000000,
      "operatingProfit": 3511000000,
      "ordinaryProfit": null,
      "profit": 2467000000,
      "totalAssets": 44716000000,
      "equity": 33497000000,
      "cashAndEquivalents": null,
      "sharesOutstanding": 24534823
    }
  ],
  "strategies": {
    "kiyohara": {
      "score": 9,
      "components": {
        "ncrScore": 9,
        "cnperScore": 0,
        "sizeBonus": 0
      },
      "reason": "NCR=-0.30, CNPER=20.0, 380億円 → 対象外"
    }
  }
}