{
  "profile": {
    "code": "7839",
    "name": "ＳＨＯＥＩ",
    "sector33Name": "その他製品",
    "sector33Code": "3800",
    "sector17Code": "10",
    "marketSegment": "プライム",
    "scaleCategory": "TOPIX Small 1",
    "updatedAt": "2026-04-26T09:37:44.961Z",
    "snapshots": [
      {
        "id": "static-7839",
        "snapshotAt": "2026-04-26T09:37:44.961Z",
        "marketCap": 92168136622,
        "netCash": -5613000000,
        "netCashRatio": -0.06089957121537607,
        "cashNeutralPer": 15.476596489711934,
        "per": 14.588182434631213,
        "pbr": 2.8592566037536837
      }
    ]
  },
  "history": [
    {
      "id": "static-7839-2025-FY",
      "code": "7839",
      "fiscalYear": 2025,
      "typeOfCurrentPeriod": "FY",
      "disclosedDate": "2025-11-14T00:00:00.000Z",
      "periodEndDate": "2025-09-30T00:00:00.000Z",
      "netSales": 32363000000,
      "operatingProfit": 8899000000,
      "ordinaryProfit": null,
      "profit": 6318000000,
      "totalAssets": 37848000000,
      "equity": 32235000000,
      "cashAndEquivalents": 19941000000,
      "sharesOutstanding": 52577374
    }
  ],
  "strategies": {
    "kiyohara": {
      "score": 0,
      "components": {
        "ncrScore": 10,
        "cnperScore": 0,
        "sizeBonus": -10
      },
      "reason": "NCR=-0.06, CNPER=15.5, 大型株ペナルティ → 対象外"
    }
  }
}