{
  "profile": {
    "code": "7972",
    "name": "イトーキ",
    "sector33Name": "その他製品",
    "sector33Code": "3800",
    "sector17Code": "10",
    "marketSegment": "プライム",
    "scaleCategory": "TOPIX Small 1",
    "updatedAt": "2026-04-26T09:37:45.008Z",
    "snapshots": [
      {
        "id": "static-7972",
        "snapshotAt": "2026-04-26T09:37:45.008Z",
        "marketCap": 128509833456,
        "netCash": -68586000000,
        "netCashRatio": -0.5337023491162091,
        "cashNeutralPer": 25.733886075989034,
        "per": 16.778931121034077,
        "pbr": 2.338583371960984
      }
    ]
  },
  "history": [
    {
      "id": "static-7972-2025-3Q",
      "code": "7972",
      "fiscalYear": 2025,
      "typeOfCurrentPeriod": "3Q",
      "disclosedDate": "2025-10-31T00:00:00.000Z",
      "periodEndDate": "2025-09-30T00:00:00.000Z",
      "netSales": 112458000000,
      "operatingProfit": 11613000000,
      "ordinaryProfit": null,
      "profit": 7659000000,
      "totalAssets": 123538000000,
      "equity": 54952000000,
      "cashAndEquivalents": null,
      "sharesOutstanding": 49407856
    }
  ],
  "strategies": {
    "kiyohara": {
      "score": 0,
      "components": {
        "ncrScore": 7,
        "cnperScore": -8,
        "sizeBonus": -10
      },
      "reason": "NCR=-0.53, CNPER=25.7, 大型株ペナルティ → 対象外"
    }
  }
}